{
  "db_name": "SQLite",
  "query": "INSERT INTO\n  `station` (`name`)\nVALUES\n  (?1)\nRETURNING\n  `id`,\n  `name`;\n",
  "describe": {
    "columns": [
      {
        "name": "id",
        "ordinal": 0,
        "type_info": "Int64"
      },
      {
        "name": "name",
        "ordinal": 1,
        "type_info": "Text"
      }
    ],
    "parameters": {
      "Right": 1
    },
    "nullable": [
      false,
      false
    ]
  },
  "hash": "a2d038245924ee8cca701d8170849acd120ed669a2083cccb45d4e2bd3868b02"
}
